app/__init__.py
app/main.py
omenicli-0.2.3.dist-info/LICENSE
omenicli-0.2.3.dist-info/METADATA
omenicli-0.2.3.dist-info/WHEEL
omenicli-0.2.3.dist-info/entry_points.txt
omenicli-0.2.3.dist-info/top_level.txt
omenicli-0.2.3.dist-info/RECORD
