Metadata-Version: 2.1
Name: omenicli
Version: 0.2.3
Summary: A powerful command-line interface for interacting with AI models and generating images. Features multiple AI providers, streaming responses, and a colorful interface.
Home-page: https://github.com/Amul-Thantharate/OmniChat-Cli.git
Author: Amul Thantharate
Author-email: amulthantharate@gmail.com
License: MIT
Classifier: Development Status :: 3 - Alpha
Classifier: Intended Audience :: Developers
Classifier: License :: OSI Approved :: MIT License
Classifier: Operating System :: OS Independent
Classifier: Programming Language :: Python :: 3
Classifier: Programming Language :: Python :: 3.10
Classifier: Programming Language :: Python :: 3.11
Classifier: Programming Language :: Python :: 3.12
Classifier: Topic :: Utilities
Classifier: Topic :: Software Development :: Libraries :: Python Modules
Requires-Python: >=3.10
License-File: LICENSE
